odoo8_addon_l10n_es_payment_order_confirming_popular-8.0.1.0.0.99.dev3-py3.6-nspkg.pth
odoo_addons/l10n_es_payment_order_confirming_popular/README.rst
odoo_addons/l10n_es_payment_order_confirming_popular/__init__.py
odoo_addons/l10n_es_payment_order_confirming_popular/__openerp__.py
odoo_addons/l10n_es_payment_order_confirming_popular/data/payment_type_data.xml
odoo_addons/l10n_es_payment_order_confirming_popular/i18n/ca.po
odoo_addons/l10n_es_payment_order_confirming_popular/i18n/es.po
odoo_addons/l10n_es_payment_order_confirming_popular/i18n/l10n_es_payment_order_confirming_popular.pot
odoo_addons/l10n_es_payment_order_confirming_popular/models/__init__.py
odoo_addons/l10n_es_payment_order_confirming_popular/models/payment_mode.py
odoo_addons/l10n_es_payment_order_confirming_popular/static/description/icon.png
odoo_addons/l10n_es_payment_order_confirming_popular/views/payment_mode_view.xml
odoo_addons/l10n_es_payment_order_confirming_popular/wizard/__init__.py
odoo_addons/l10n_es_payment_order_confirming_popular/wizard/confirming_popular.py
odoo_addons/l10n_es_payment_order_confirming_popular/wizard/export_csb.py
odoo8_addon_l10n_es_payment_order_confirming_popular-8.0.1.0.0.99.dev3.dist-info/METADATA
odoo8_addon_l10n_es_payment_order_confirming_popular-8.0.1.0.0.99.dev3.dist-info/WHEEL
odoo8_addon_l10n_es_payment_order_confirming_popular-8.0.1.0.0.99.dev3.dist-info/namespace_packages.txt
odoo8_addon_l10n_es_payment_order_confirming_popular-8.0.1.0.0.99.dev3.dist-info/top_level.txt
odoo8_addon_l10n_es_payment_order_confirming_popular-8.0.1.0.0.99.dev3.dist-info/RECORD
